wise_yoda/__init__.py
wise_yoda/cli.py
wise_yoda/data/quotes.json
wise_yoda/wisdom.py
wiseyoda-1.0.1.dist-info/LICENSE
wiseyoda-1.0.1.dist-info/WHEEL
wiseyoda-1.0.1.dist-info/entry_points.txt
wiseyoda-1.0.1.dist-info/METADATA
wiseyoda-1.0.1.dist-info/RECORD
