Metadata-Version: 2.1
Name: wiseyoda
Version: 1.0.1
Summary: Quote the wise and powerful master Yoda.
Home-page: https://github.com/Mikaayenson/WiseYoda
License: Apache 2.0
Keywords: Star Wars,Yoda,Quotes
Author: Mika Ayenson
Author-email: Mika.ayenson@elastic.co
Requires-Python: >=3.8,<4.0
Classifier: Development Status :: 4 - Beta
Classifier: Environment :: Console
Classifier: License :: OSI Approved :: Apache Software License
Classifier: License :: Other/Proprietary License
Classifier: Operating System :: MacOS
Classifier: Programming Language :: Python :: 3
Classifier: Programming Language :: Python :: 3.8
Classifier: Programming Language :: Python :: 3.9
Classifier: Programming Language :: Python :: 3.10
Classifier: Programming Language :: Python :: 3.11
Classifier: Programming Language :: Python :: 3
Classifier: Programming Language :: Python :: 3.10
Classifier: Programming Language :: Python :: 3.8
Classifier: Programming Language :: Python :: 3.9
Classifier: Topic :: Security
Classifier: Typing :: Typed
Requires-Dist: marshmallow-dataclass (>=8.5.10,<9.0.0)
Project-URL: Bug Tracker, https://github.com/Mikaayenson/WiseYoda/issues
Project-URL: Repository, https://github.com/Mikaayenson/WiseYoda
